core/__init__.py
core/utils.py
mooncake-0.0.1.dist-info/LICENSE
mooncake-0.0.1.dist-info/METADATA
mooncake-0.0.1.dist-info/WHEEL
mooncake-0.0.1.dist-info/top_level.txt
mooncake-0.0.1.dist-info/RECORD
